pytgpt_bot/__init__.py
pytgpt_bot/__main__.py
pytgpt_bot/cli.py
pytgpt_bot/config.py
pytgpt_bot/db.py
pytgpt_bot/filters.py
pytgpt_bot/main.py
pytgpt_bot/models.py
pytgpt_bot/utils.py
pytgpt_bot-0.1.7.4.dist-info/LICENSE
pytgpt_bot-0.1.7.4.dist-info/METADATA
pytgpt_bot-0.1.7.4.dist-info/WHEEL
pytgpt_bot-0.1.7.4.dist-info/entry_points.txt
pytgpt_bot-0.1.7.4.dist-info/top_level.txt
pytgpt_bot-0.1.7.4.dist-info/RECORD
