Metadata-Version: 2.1
Name: pytgpt-bot
Version: 0.1.7.4
Summary: AI powered Telegram bot for chatting, text-to-image and text-to-speech conversions
Home-page: https://github.com/Simatwa/pytgpt-bot
Author: Smartwa
Author-email: simatwacaleb@proton.me
Maintainer: Smartwa
License: MIT
Project-URL: Bug Report, https://github.com/Simatwa/pytgpt-bot/issues/new
Project-URL: Homepage, https://github.com/Simatwa/pytgpt-bot
Project-URL: Source Code, https://github.com/Simatwa/pytgpt-bot
Project-URL: Issue Tracker, https://github.com/Simatwa/pytgpt-bot/issues
Project-URL: Download, https://github.com/Simatwa/pytgpt-bot/releases
Project-URL: Documentation, https://github.com/Simatwa/pytgpt-bot/blob/main/README.md
Keywords: ai,tgpt,pytgpt,chatbot,telegrambot,pytelegrambot,chatbot,text-to-speech,text-to-image
Classifier: License :: OSI Approved :: MIT License
Classifier: Intended Audience :: Developers
Classifier: Intended Audience :: Developers
Classifier: Natural Language :: English
Classifier: License :: Free For Home Use
Classifier: Intended Audience :: Customer Service
Classifier: Programming Language :: Python
Classifier: Topic :: Software Development :: Libraries :: Python Modules
Classifier: Topic :: Scientific/Engineering :: Artificial Intelligence
Classifier: Programming Language :: Python :: 3 :: Only
Classifier: Programming Language :: Python :: 3.10
Classifier: Programming Language :: Python :: 3.10
Classifier: Programming Language :: Python :: 3.11
Classifier: Programming Language :: Python :: 3.12
Requires-Python: >=3.10
License-File: LICENSE
Requires-Dist: pytelegrambotapi ==4.17.0
Requires-Dist: python-tgpt ==0.7.0
Requires-Dist: python-dotenv ==1.0.0
Requires-Dist: click ==8.1.3
Requires-Dist: SQLAlchemy ==2.0.29
